hpdb/__init__.py
hpdb/dbclass.py
hpdb-4.0.7.dist-info/LICENSE
hpdb-4.0.7.dist-info/METADATA
hpdb-4.0.7.dist-info/WHEEL
hpdb-4.0.7.dist-info/top_level.txt
hpdb-4.0.7.dist-info/RECORD
