Metadata-Version: 2.1
Name: hpdb
Version: 4.0.7
Summary: Makes working with existing sql databases super easy
Author-email: HP Harmsen <hp@harmsen.nl>
License: This is free and unencumbered software released into the public domain.
Project-URL: Homepage, https://github.com/hpharmsen/hpdb
Keywords: mysql,postgresql
Classifier: Programming Language :: Python
Classifier: Programming Language :: Python :: 3
Requires-Python: >=3.7
License-File: LICENSE
Requires-Dist: sqlalchemy
Requires-Dist: sqlparse
Requires-Dist: pandas
Provides-Extra: dev
Requires-Dist: black ; extra == 'dev'
Requires-Dist: build ; extra == 'dev'
Requires-Dist: twine ; extra == 'dev'
